phasemap/__init__.py
phasemap/_box.py
phasemap/_cache.py
phasemap/_coordinate.py
phasemap/_logging_setup.py
phasemap/_result.py
phasemap/_run.py
phasemap/plot.py
phasemap/io/__init__.py
phasemap/io/_encoding.py
phasemap/io/_save_load.py
phasemap-0.1.0.dist-info/METADATA
phasemap-0.1.0.dist-info/RECORD
phasemap-0.1.0.dist-info/WHEEL
phasemap-0.1.0.dist-info/top_level.txt
